ldplayer/__init__.py
ldplayer/controller.py
ldplayer/ldplayer.py
ldplayer_tools-0.0.3.dist-info/LICENSE
ldplayer_tools-0.0.3.dist-info/METADATA
ldplayer_tools-0.0.3.dist-info/WHEEL
ldplayer_tools-0.0.3.dist-info/top_level.txt
ldplayer_tools-0.0.3.dist-info/RECORD
